AUTHORS.md
CHANGES.md
HACKING.md
INSTALL.md
MANIFEST.in
README.md
setup.py
config/browser.cfg
deepify/__init__.py
deepify/tor.py
deepify/zeronet.py
deepify.egg-info/PKG-INFO
deepify.egg-info/SOURCES.txt
deepify.egg-info/dependency_links.txt
deepify.egg-info/requires.txt
deepify.egg-info/top_level.txt
deepify/utils/__init__.py
deepify/utils/banner.py
deepify/utils/configuration.py
deepify/utils/wrapper.py
scripts/onionGet.py
scripts/onionsFromFile.py
scripts/zeronetGet.py
scripts/zeronetsFromFile.py