Metadata-Version: 1.1
Name: deepify
Version: 0.3.2
Summary: Deepify - A set of GPLv3+ libraries to deal with Deepweb connections.
Home-page: http://github.com/i3visio/deepify
Author: Felix Brezo and Yaiza Rubio
Author-email: contacto@i3visio.com
License: COPYING
Keywords: python osint harvesting networking tor zeronet privacy
Platform: UNKNOWN
Classifier: Development Status :: 4 - Beta
Classifier: Topic :: Software Development :: Libraries
Classifier: License :: OSI Approved :: GNU General Public License v3 or later (GPLv3+)
Classifier: Programming Language :: Python :: 2 :: Only
Classifier: Programming Language :: Python :: 2.7
Classifier: Intended Audience :: Developers
Classifier: Intended Audience :: Information Technology
Classifier: Intended Audience :: Science/Research
Classifier: Intended Audience :: Telecommunications Industry
Classifier: Natural Language :: English
Classifier: Topic :: Communications
Classifier: Topic :: Internet :: WWW/HTTP :: Indexing/Search
Classifier: Topic :: Text Processing :: Markup :: HTML
